wordsearch/__init__.py
wordsearch/masks.py
wordsearch/wordsearch.py
python_wordsearch-1.0.1.dist-info/LICENSE
python_wordsearch-1.0.1.dist-info/METADATA
python_wordsearch-1.0.1.dist-info/WHEEL
python_wordsearch-1.0.1.dist-info/top_level.txt
python_wordsearch-1.0.1.dist-info/RECORD
