Metadata-Version: 2.1
Name: python-wordsearch
Version: 1.0.1
Summary: A package for creating word searches
Home-page: https://github.com/scipython/python-wordsearch
Author: Christian Hill
Author-email: xn.hill@gmail.com
Project-URL: Bug Reports, https://github.com/scipython/python-wordsearch/issues
Keywords: wordsearch,puzzle
Classifier: Development Status :: 4 - Beta
Classifier: Intended Audience :: Other Audience
Classifier: Intended Audience :: Education
Classifier: Topic :: Games/Entertainment
Classifier: Topic :: Games/Entertainment :: Puzzle Games
Classifier: License :: OSI Approved :: GNU General Public License v3 (GPLv3)
Classifier: Programming Language :: Python :: 3
Classifier: Programming Language :: Python :: 3.6
Classifier: Programming Language :: Python :: 3.7
Classifier: Programming Language :: Python :: 3.8
Classifier: Programming Language :: Python :: 3.9
Classifier: Programming Language :: Python :: 3.10
Classifier: Programming Language :: Python :: 3 :: Only
Classifier: Operating System :: OS Independent
Requires-Python: >=3.6
License-File: LICENSE
Provides-Extra: dev
Requires-Dist: black ; extra == 'dev'
Requires-Dist: pytest-cov ; extra == 'dev'
Requires-Dist: tox ; extra == 'dev'
Requires-Dist: ipython ; extra == 'dev'
Requires-Dist: sphinx ; extra == 'dev'
